sdk/__init__.py
sdk/client.py
sdk/constants/__init__.py
sdk/constants/enums.py
sdk/globals.py
sdk/primitive.py
sdk/resources/__init__.py
sdk/resources/parameters.py
sdk/resources/resources.py
sdk/task.py
llmrun-0.0.0.dist-info/METADATA
llmrun-0.0.0.dist-info/WHEEL
llmrun-0.0.0.dist-info/RECORD
